eodc/__init__.py
eodc/auth.py
eodc/dask.py
eodc/faas.py
eodc/settings.py
eodc/storage.py
eodc/visualisation/__init__.py
eodc/visualisation/vessel_detection/__init__.py
eodc/visualisation/vessel_detection/app.py
eodc/visualisation/vessel_detection/assets/app.css
eodc/visualisation/vessel_detection/cards.py
eodc/visualisation/vessel_detection/navbar.py
eodc/visualisation/vessel_detection/utils.py
eodc/workspace.py
eodc-2025.10.1.dist-info/LICENSE
eodc-2025.10.1.dist-info/METADATA
eodc-2025.10.1.dist-info/WHEEL
eodc-2025.10.1.dist-info/RECORD
