Metadata-Version: 2.1
Name: eodc
Version: 2025.10.1
Summary: Python SDK for interacting with EODC services.
Home-page: https://github.com/eodcgmbh/eodc-sdk
Author: Lukas Weidenholzer
Author-email: lukas.weidenholzer@eodc.eu
Maintainer: EODC Staff
Maintainer-email: support@eodc.eu
Requires-Python: >=3.10,<3.13
Classifier: Development Status :: 1 - Planning
Classifier: Intended Audience :: Developers
Classifier: Programming Language :: Python
Classifier: Programming Language :: Python :: 3
Classifier: Programming Language :: Python :: 3.10
Classifier: Programming Language :: Python :: 3.11
Classifier: Programming Language :: Python :: 3 :: Only
Classifier: Programming Language :: Python :: 3.9
Requires-Dist: OWSLib (>=0.29.3,<0.30.0)
Requires-Dist: azure-identity (>=1.15.0,<2.0.0)
Requires-Dist: azure-storage-blob (>=12.18.3,<13.0.0)
Requires-Dist: boto3 (==1.34.145)
Requires-Dist: dash (>=2.15.0,<3.0.0)
Requires-Dist: dash-bootstrap-components (>=1.5.0,<2.0.0)
Requires-Dist: dash-extensions (>=1.0.11,<2.0.0)
Requires-Dist: dash_daq (>=0.5.0,<0.6.0)
Requires-Dist: dash_leaflet (>=1.0.15,<2.0.0)
Requires-Dist: dask-gateway (>=2023.1.1)
Requires-Dist: geopandas (>=0.14.3,<0.15.0)
Requires-Dist: hera (>=5.14.0,<5.15.1)
Requires-Dist: httpx (>=0.27.0,<0.28.0)
Requires-Dist: jsbeautifier (>=1.14.11,<2.0.0)
Requires-Dist: minio (>=7.1.16,<8.0.0)
Requires-Dist: nbformat (>4.2.0)
Requires-Dist: openeo-pg-parser-networkx (>=2025.9.1)
Requires-Dist: openeo[localprocessing] (>=0.13.0,<1)
Requires-Dist: plotly (>=5.18.0,<6.0.0)
Requires-Dist: pydantic (>=2.0.1,<3.0.0)
Requires-Dist: pydantic-settings (>=2.3.4,<3.0.0)
Requires-Dist: pyjwt[crypto] (>=2.8.0,<3.0.0)
Requires-Dist: pyproj (>=3.6.0,<4.0.0)
Requires-Dist: pystac (>=1.7.3,<2.0.0)
Requires-Dist: requests (>=2.28.2,<3.0.0)
Project-URL: Repository, https://github.com/eodcgmbh/eodc-sdk
